PySFO/__init__.py
PySFO-2.0.0.dist-info/METADATA
PySFO-2.0.0.dist-info/WHEEL
PySFO-2.0.0.dist-info/top_level.txt
PySFO-2.0.0.dist-info/RECORD
