Metadata-Version: 2.1
Name: PySFO
Version: 2.0.0
Summary: Get SFO!
Author: FlipFlapsRU
Requires-Python: >=3.7
